Metadata-Version: 1.0
Name: twisted-json-socket2
Version: 0.1.4
Summary: Protocol for twisted json socket
Home-page: https://bitbucket.org/madssj/twisted-json-socket
Author: Bo Kanstrup, Mads Sülau Jørgensen
Author-email: mads@sulau.dk
License: BSD
Keywords: twsited json socket protocol
Platform: UNKNOWN
